confluxuate/__init__.py
confluxuate-0.1.0.dist-info/LICENSE
confluxuate-0.1.0.dist-info/METADATA
confluxuate-0.1.0.dist-info/WHEEL
confluxuate-0.1.0.dist-info/RECORD
